odoo/addons/account_analytic_account_tag/README.rst
odoo/addons/account_analytic_account_tag/__init__.py
odoo/addons/account_analytic_account_tag/__manifest__.py
odoo/addons/account_analytic_account_tag/i18n/account_analytic_account_tag.pot
odoo/addons/account_analytic_account_tag/i18n/fr.po
odoo/addons/account_analytic_account_tag/i18n/it.po
odoo/addons/account_analytic_account_tag/models/__init__.py
odoo/addons/account_analytic_account_tag/models/account_analytic_account.py
odoo/addons/account_analytic_account_tag/readme/CONTRIBUTORS.md
odoo/addons/account_analytic_account_tag/readme/DESCRIPTION.md
odoo/addons/account_analytic_account_tag/static/description/icon.png
odoo/addons/account_analytic_account_tag/static/description/index.html
odoo/addons/account_analytic_account_tag/views/account_analytic_account_views.xml
odoo_addon_account_analytic_account_tag-17.0.1.0.0.2.dist-info/METADATA
odoo_addon_account_analytic_account_tag-17.0.1.0.0.2.dist-info/WHEEL
odoo_addon_account_analytic_account_tag-17.0.1.0.0.2.dist-info/top_level.txt
odoo_addon_account_analytic_account_tag-17.0.1.0.0.2.dist-info/RECORD
