Metadata-Version: 2.1
Name: odoo-addon-account_analytic_account_tag
Version: 17.0.1.0.0.2
Requires-Python: >=3.10
Requires-Dist: odoo-addon-account_analytic_tag>=17.0dev,<17.1dev
Requires-Dist: odoo>=17.0a,<17.1dev
Summary: Restore the tag_ids in account.analytic.account
Home-page: https://github.com/OCA/account-analytic
License: AGPL-3
Author: ACSONE SA/NV, Odoo Community Association (OCA)
Author-email: support@odoo-community.org
Classifier: Programming Language :: Python
Classifier: Framework :: Odoo
Classifier: Framework :: Odoo :: 17.0
Classifier: License :: OSI Approved :: GNU Affero General Public License v3
